{"type":"FeatureCollection","crs":{"type":"name","properties":{"name":"EPSG:6668"}},"features":[{"type":"Feature","id":0,"geometry":{"type":"Point","coordinates":[139.73102385504507,35.664545978121339]},"properties":{"FID":0,"id":"e627bf1aead14f42a0fcb83f4296c93f","category":"F013","floor_id":"9bbb5072868648ee91998f76a129bcc7","name":" ","source":"2"}},{"type":"Feature","id":1,"geometry":{"type":"Point","coordinates":[139.73103442646149,35.664558109694418]},"properties":{"FID":1,"id":"c4c3c4eede224eae8e4edeef7b184257","category":"F011","floor_id":"9bbb5072868648ee91998f76a129bcc7","name":" ","source":"2"}},{"type":"Feature","id":2,"geometry":{"type":"Point","coordinates":[139.73141667522032,35.663981964626039]},"properties":{"FID":2,"id":"07816287e097410b8412122b981e9fac","category":"F015","floor_id":"9bbb5072868648ee91998f76a129bcc7","name":" ","source":"2"}},{"type":"Feature","id":3,"geometry":{"type":"Point","coordinates":[139.73138956789688,35.663969668706237]},"properties":{"FID":3,"id":"fd85386f699349829965309108ba5e77","category":"F014","floor_id":"9bbb5072868648ee91998f76a129bcc7","name":" ","source":"2"}},{"type":"Feature","id":4,"geometry":{"type":"Point","coordinates":[139.73185505696492,35.663569001891005]},"properties":{"FID":4,"id":"bf7b79d4c7fb4341b7704cc02cce450f","category":"F014","floor_id":"9bbb5072868648ee91998f76a129bcc7","name":" ","source":"2"}},{"type":"Feature","id":5,"geometry":{"type":"Point","coordinates":[139.73193568636398,35.663501314447352]},"properties":{"FID":5,"id":"28843a84cb064c2ca05fe13a3409a4a5","category":"F011","floor_id":"9bbb5072868648ee91998f76a129bcc7","name":" ","source":"2"}},{"type":"Feature","id":6,"geometry":{"type":"Point","coordinates":[139.73192094895518,35.663482916990539]},"properties":{"FID":6,"id":"80f2e1db21b647f485a5ab105cd675b0","category":"F013","floor_id":"9bbb5072868648ee91998f76a129bcc7","name":" ","source":"2"}}]}
