{"type":"FeatureCollection","crs":{"type":"name","properties":{"name":"EPSG:6668"}},"features":[{"type":"Feature","id":0,"geometry":{"type":"Point","coordinates":[139.73054140531903,35.66484470112669]},"properties":{"FID":0,"id":"1509cb1435ad454faa092fc7523b7f8a","category":"F013","floor_id":"f556ee28b9144f30a99bbf60a7e30c4b","name":" ","source":"2"}},{"type":"Feature","id":1,"geometry":{"type":"Point","coordinates":[139.7305299202582,35.664834591520005]},"properties":{"FID":1,"id":"aac72617d5a44cd89dda8a800f48dc06","category":"F013","floor_id":"f556ee28b9144f30a99bbf60a7e30c4b","name":" ","source":"2"}},{"type":"Feature","id":2,"geometry":{"type":"Point","coordinates":[139.73038522659667,35.66480081383632]},"properties":{"FID":2,"id":"1db9f9bae5ec45859fa7e3232780fbe4","category":"F011","floor_id":"f556ee28b9144f30a99bbf60a7e30c4b","name":" ","source":"2"}},{"type":"Feature","id":3,"geometry":{"type":"Point","coordinates":[139.73045950907593,35.66478119782988]},"properties":{"FID":3,"id":"c90a6c2c0b1c49209352c072d4d9412a","category":"F011","floor_id":"f556ee28b9144f30a99bbf60a7e30c4b","name":" ","source":"2"}},{"type":"Feature","id":4,"geometry":{"type":"Point","coordinates":[139.73047714108466,35.66481482478819]},"properties":{"FID":4,"id":"c8566e67795642c58bc846fee57c92af","category":"F013","floor_id":"f556ee28b9144f30a99bbf60a7e30c4b","name":" ","source":"2"}},{"type":"Feature","id":5,"geometry":{"type":"Point","coordinates":[139.7304650430664,35.66480433508387]},"properties":{"FID":5,"id":"be8b506ca4b84956940481b2598e9fa5","category":"F013","floor_id":"f556ee28b9144f30a99bbf60a7e30c4b","name":" ","source":"2"}},{"type":"Feature","id":6,"geometry":{"type":"Point","coordinates":[139.73181720237616,35.66366465906894]},"properties":{"FID":6,"id":"c5482747ff2e4e39b9ffcd5936d0bbe9","category":"F011","floor_id":"7fa341a97c8a456b83fdcfd3a043ff00","name":" ","source":"2"}},{"type":"Feature","id":7,"geometry":{"type":"Point","coordinates":[139.73182823180628,35.66368085846865]},"properties":{"FID":7,"id":"09b3f67c16484907b750aea3bee4ac64","category":"F013","floor_id":"7fa341a97c8a456b83fdcfd3a043ff00","name":" ","source":"2"}},{"type":"Feature","id":8,"geometry":{"type":"Point","coordinates":[139.73184162009466,35.66368809842277]},"properties":{"FID":8,"id":"6eeb898e21ee4b68aae18bde0f3dacc7","category":"F013","floor_id":"7fa341a97c8a456b83fdcfd3a043ff00","name":" ","source":"2"}},{"type":"Feature","id":9,"geometry":{"type":"Point","coordinates":[139.731729776771,35.6637085244133]},"properties":{"FID":9,"id":"13cc2b9f83094a609c28a1482d4a6e88","category":"F011","floor_id":"7fa341a97c8a456b83fdcfd3a043ff00","name":" ","source":"2"}},{"type":"Feature","id":10,"geometry":{"type":"Point","coordinates":[139.7317141894948,35.66369731291088]},"properties":{"FID":10,"id":"a7c58d1bc3a245099cc5eca1b9085e25","category":"F013","floor_id":"7fa341a97c8a456b83fdcfd3a043ff00","name":" ","source":"2"}},{"type":"Feature","id":11,"geometry":{"type":"Point","coordinates":[139.73169951076855,35.66368862496594]},"properties":{"FID":11,"id":"a119950e4b0a41f6ab4152905624a99e","category":"F013","floor_id":"7fa341a97c8a456b83fdcfd3a043ff00","name":" ","source":"2"}}]}
